LICENSE.md
README.md
pyproject.toml
setup.cfg
setup.py
src/ewoksid11/__init__.py
src/ewoksid11/constants.py
src/ewoksid11/pdfgetx_average.py
src/ewoksid11/pdfgetx_config.py
src/ewoksid11/pdfgetx_processor.py
src/ewoksid11/pdfgetx_save_ascii.py
src/ewoksid11/pdfgetx_save_nexus.py
src/ewoksid11/pyfai_calib_average.py
src/ewoksid11/pyfai_calib_save.py
src/ewoksid11.egg-info/PKG-INFO
src/ewoksid11.egg-info/SOURCES.txt
src/ewoksid11.egg-info/dependency_links.txt
src/ewoksid11.egg-info/entry_points.txt
src/ewoksid11.egg-info/requires.txt
src/ewoksid11.egg-info/top_level.txt
src/ewoksid11/tests/__init__.py
src/ewoksid11/tests/conftest.py
src/ewoksid11/tests/test_pdfgetx_average.py
src/ewoksid11/tests/test_pdfgetx_config.py
src/ewoksid11/tests/test_pdfgetx_processor.py
src/ewoksid11/tests/test_pdfgetx_save_ascii.py
src/ewoksid11/tests/test_pdfgetx_save_nexus.py
src/ewoksid11/tests/test_pyfai_calib_average.py
src/ewoksid11/tests/test_pyfai_calib_save.py
src/ewoksid11/tests/data/__init__.py
src/ewoksid11/tests/data/frelon.spline
src/ewoksid11/tests/data/pdfexample/CeO2.dat
src/ewoksid11/tests/data/pdfexample/CeO2.fq
src/ewoksid11/tests/data/pdfexample/CeO2.gr
src/ewoksid11/tests/data/pdfexample/CeO2.h5
src/ewoksid11/tests/data/pdfexample/CeO2.iq
src/ewoksid11/tests/data/pdfexample/CeO2.sq
src/ewoksid11/tests/data/pdfexample/CeO2_processed.h5
src/ewoksid11/tests/data/pdfexample/__init__.py
src/ewoksid11/tests/data/pdfexample/background.xy
src/ewoksid11/tests/data/pdfexample/config.cfg