Metadata-Version: 2.1
Name: ewoksid11
Version: 0.1.0
Summary: Data processing workflows for ID11
Home-page: https://gitlab.esrf.fr/workflow/ewoksid11/
Author: ESRF
Author-email: wout.de_nolf@esrf.fr
License: MIT
Project-URL: Source, https://gitlab.esrf.fr/workflow/ewoksid11/
Project-URL: Documentation, https://ewoksid11.readthedocs.io/
Project-URL: Tracker, https://gitlab.esrf.fr/workflow/ewoksid11/issues/
Keywords: ewoks
Classifier: Intended Audience :: Science/Research
Classifier: License :: OSI Approved :: MIT License
Classifier: Programming Language :: Python :: 3
Requires-Python: >=3.7
License-File: LICENSE.md
Requires-Dist: ewoksxrpd
Provides-Extra: test
Requires-Dist: pytest>=7; extra == "test"
Provides-Extra: dev
Requires-Dist: pytest>=7; extra == "dev"
Requires-Dist: black>=22; extra == "dev"
Requires-Dist: flake8>=4; extra == "dev"
Provides-Extra: doc
Requires-Dist: pytest>=7; extra == "doc"
Requires-Dist: sphinx>=4.5; extra == "doc"
Requires-Dist: sphinx-autodoc-typehints>=1.16; extra == "doc"
Requires-Dist: pydata-sphinx-theme; extra == "doc"
